baselibs/__init__.py
baselibs/baselibs.py
baselibs/llm_task.py
baselibs/mtask_lib.py
baselibs/optimized_timer.py
baselibs/qrlib.py
baselibs/rediscache.py
baselibs/simple_timer.py
baselibs/test_baselibs.py
baselibs/test_llm_task.py
baselibs/test_mtask_lib.py
baselibs/test_rediscache.py
baselibs/test_simple_timer.py
baselibs-0.1.14.dist-info/LICENSE
baselibs-0.1.14.dist-info/METADATA
baselibs-0.1.14.dist-info/WHEEL
baselibs-0.1.14.dist-info/top_level.txt
baselibs-0.1.14.dist-info/RECORD
