Metadata-Version: 2.1
Name: baselibs
Version: 0.1.14
Summary: baselibs
Home-page: https://github.com/xmxoxo/baselibs
Author: He xi
Author-email: xmhexi@qq.com
Project-URL: Blog, https://blog.csdn.net/xmxoxo
Keywords: baselibs
Classifier: Development Status :: 4 - Beta
Classifier: Intended Audience :: Developers
Classifier: Topic :: Software Development :: Code Generators
Classifier: License :: OSI Approved :: MIT License
Classifier: Programming Language :: Python :: 3.8
Classifier: Programming Language :: Python :: 3.9
Classifier: Programming Language :: Python :: 3.10
Classifier: Programming Language :: Python :: 3.11
License-File: LICENSE
Requires-Dist: fire>=0.5.0
Requires-Dist: numpy>=1.20.0
Requires-Dist: pandas>=1.5.3
Requires-Dist: redis>=5.0.6
Requires-Dist: scikit-learn>=0.22.2
Requires-Dist: requests>=2.32.3
Requires-Dist: openai>=1.28.0
Requires-Dist: httpx==0.27.0
